idleopenline/__init__.py
idleopenline/extension.py
idleopenline/py.typed
idleopenline/utils.py
idleopenline-0.0.2.dist-info/licenses/LICENSE
idleopenline-0.0.2.dist-info/METADATA
idleopenline-0.0.2.dist-info/WHEEL
idleopenline-0.0.2.dist-info/entry_points.txt
idleopenline-0.0.2.dist-info/top_level.txt
idleopenline-0.0.2.dist-info/RECORD
